{
  "guide": {
    "Basic Tax filing": {
      "manual": "This guide explains the necessary details required for filing basic tax"
    },
    "Child Benifits": {
      "manual": "This guide explains the necessary details required for Child Benifits"
    },
    "Ontario Trillium Benifits": {
      "manual": "This guide explains the necessary details required for Ontario Trillium Benifits"
    },
    "GST/HST Credits": {
      "manual": "This guide explains the necessary details required for GST/HST Credits"
    }
  }
} 